ssvc/__init__.py
ssvc/core.py
ssvc/legacy.py
ssvc/plugins/__init__.py
ssvc/plugins/ai_llm_triage.py
ssvc/plugins/cisa.py
ssvc/plugins/coordinator_publication.py
ssvc/plugins/coordinator_triage.py
ssvc/plugins/deployer.py
ssvc/plugins/supplier.py
ssvc-1.2.3.dist-info/licenses/LICENSE
ssvc-1.2.3.dist-info/METADATA
ssvc-1.2.3.dist-info/WHEEL
ssvc-1.2.3.dist-info/top_level.txt
ssvc-1.2.3.dist-info/RECORD
