Metadata-Version: 2.4
Name: ssvc
Version: 1.2.3
Summary: A Python implementation of the Stakeholder-Specific Vulnerability Categorization framework.
Author-email: Christopher Langton <chris@vulnetix.com>
License: Copyright 2024 Christopher Langton
Project-URL: Homepage, https://www.vulnetix.com
Project-URL: Repository, https://github.com/vulnetix/python-ssvc.git
Requires-Python: >=3.11
License-File: LICENSE
Requires-Dist: PyYAML>=6.0
Requires-Dist: jsonschema>=4.0.0
Provides-Extra: test
Requires-Dist: pytest-cov>=6.0.0; extra == "test"
Requires-Dist: pytest>=8.3.4; extra == "test"
Requires-Dist: coverage-badge>=1.1.2; extra == "test"
Provides-Extra: sec
Requires-Dist: pip-audit>=2.7.3; extra == "sec"
Provides-Extra: dev
Requires-Dist: PyYAML>=6.0; extra == "dev"
Dynamic: license-file
